idman/__init__.py
idman-0.0.0.dist-info/METADATA
idman-0.0.0.dist-info/WHEEL
idman-0.0.0.dist-info/top_level.txt
idman-0.0.0.dist-info/RECORD
