Metadata-Version: 2.1
Name: idman
Version: 0.0.0
Summary: Coming soon
Author-email: Idman <admin@idman.ai>
